{
    "databarang":[
        {
            "id": "brg01",
            "nama": "Fantech ATOM PRO SERIES Wireless Keyboard Mechanical Gaming Hotswap",
            "harga": "490.000",
            "stok": 10,
            "img": "https://images.tokopedia.net/img/cache/900/VqbcmM/2024/3/28/79bd45c3-03ef-4e06-85cf-d8c2987010f6.jpg",
            "seller": "Asep Montir Gamink",
            "deskripsi": "3 Form Factor to Choose Stellar Edition\n merupakan seri keyboard gaming mechanical ATOM PRO yang terdiri dari tiga produk dengan layout yang berbeda-beda. ATOM PRO63 MK912 dengan layout 60% ATOM PRO83 MK913 dengan layout 75% ATOM PRO96 MK914 dengan layout 95%. (Coming Soon)\n\nTri-Mode Connection ATOM PRO\n telah dilengkapi dengan fitur 3 mode konektivitas. Mulai dari koneksi wired menggunakan kabel, wireless 2.4GHz yang stabil, hingga Bluetooth yang bisa disambungkan ke 3 device sekaligus.\n\n Hot Swappable Switch & Per-Key RGB Lighting\n Telah dibekali dengan switch yang hot swappable dan kompatibel dengan mechanical switch 5 pin yang memudahkan kamu untuk memasang dan mengganti switch. Selain itu juga terdapat fitur per-key RGB lighting yang siap meningkatkan tampilan keyboard jadi semakin memukau."
        },
        {
            "id": "brg02",
            "nama": "Logitech G502 HERO High Performance Gaming Mouse",
            "harga": "500.000",
            "stok": 25,
            "img":
                "https://images.tokopedia.net/img/cache/900/VqbcmM/2024/4/27/3ad8ad82-927c-46c4-ad21-1b90c8f50240.jpg",
            "seller": "Toko Mouse Mantap",
            "deskripsi": "Logitech G502 HERO adalah gaming mouse berperforma tinggi dengan sensor HERO 25K yang canggih untuk keakuratan piksel sempurna.\n\nMouse ini juga dilengkapi dengan sistem pemberat yang dapat disesuaikan, 11 tombol yang dapat diprogram, dan RGB lighting yang dapat dikustomisasi."
        },
        {
            "id": "brg03",
            "nama": "Razer BlackShark V2 X Gaming Headset",
            "harga": "700.000",
            "stok": 50,
            "img":
                "https://images.tokopedia.net/img/cache/900/VqbcmM/2022/4/21/ac398ea7-9886-4e1e-8920-f456a8ce8376.jpg",
            "seller": "Razer Store Indonesia",
            "deskripsi": "Razer BlackShark V2 X merupakan headset gaming yang dirancang dengan fokus pada kualitas audio, kenyamanan, dan kinerja.\n\nDengan teknologi suara THX Spatial Audio, memberikan pengalaman surround sound yang imersif. Headset ini juga sangat ringan, hanya 240g, dengan busa memory foam untuk kenyamanan jangka panjang."
        },
        {
            "id": "brg04",
            "nama": "ASUS TUF Gaming F15 Gaming Laptop",
            "harga": "15.000.000",
            "stok": 15,
            "img":
                "https://images.tokopedia.net/img/cache/900/VqbcmM/2024/8/28/7d5c4636-2bb9-42b6-812c-40b0fb044409.jpg",
            "seller": "Toko Laptop Mantap",
            "deskripsi": "ASUS TUF Gaming F15 adalah laptop gaming yang tahan banting dengan kinerja luar biasa berkat prosesor Intel Core i7 generasi ke-10 dan grafis NVIDIA GeForce GTX.\n\nDilengkapi dengan layar 144Hz, memastikan pengalaman gaming yang mulus dan responsif. Laptop ini juga memiliki sertifikasi MIL-STD-810H, sehingga sangat tangguh untuk digunakan dalam kondisi ekstrim."
        },
        {
            "id": "brg05",
            "nama": "ASUS TUF Gaming F15 Gaming Laptop",
            "harga": "15.000.000",
            "stok": 0,
            "img":
                "https://images.tokopedia.net/img/cache/900/VqbcmM/2024/8/28/7d5c4636-2bb9-42b6-812c-40b0fb044409.jpg",
            "seller": "Toko Laptop Mantap",
            "deskripsi": "ASUS TUF Gaming F15 adalah laptop gaming yang tahan banting dengan kinerja luar biasa berkat prosesor Intel Core i7 generasi ke-10 dan grafis NVIDIA GeForce GTX.\n\nDilengkapi dengan layar 144Hz, memastikan pengalaman gaming yang mulus dan responsif. Laptop ini juga memiliki sertifikasi MIL-STD-810H, sehingga sangat tangguh untuk digunakan dalam kondisi ekstrim."
        }
    ]
}